molmarbles/__init__.py
molmarbles-0.1.0.dist-info/LICENSE
molmarbles-0.1.0.dist-info/METADATA
molmarbles-0.1.0.dist-info/WHEEL
molmarbles-0.1.0.dist-info/RECORD
